aiocomfoconnect/__init__.py
aiocomfoconnect/__main__.py
aiocomfoconnect/bridge.py
aiocomfoconnect/comfoconnect.py
aiocomfoconnect/const.py
aiocomfoconnect/discovery.py
aiocomfoconnect/exceptions.py
aiocomfoconnect/properties.py
aiocomfoconnect/protobuf/nanopb_pb2.py
aiocomfoconnect/protobuf/zehnder_pb2.py
aiocomfoconnect/sensors.py
aiocomfoconnect/util.py
aiocomfoconnect-0.1.15.dist-info/LICENSE
aiocomfoconnect-0.1.15.dist-info/METADATA
aiocomfoconnect-0.1.15.dist-info/WHEEL
aiocomfoconnect-0.1.15.dist-info/RECORD
