Metadata-Version: 2.1
Name: aiocomfoconnect
Version: 0.1.15
Summary: aiocomfoconnect is an asyncio Python 3 library for communicating with a Zehnder ComfoAir Q350/450/600 ventilation system
Home-page: https://github.com/michaelarnauts/aiocomfoconnect
Author: Michaël Arnauts
Author-email: michael.arnauts@gmail.com
Requires-Python: >=3.10,<4.0
Classifier: Programming Language :: Python :: 3
Classifier: Programming Language :: Python :: 3.10
Classifier: Programming Language :: Python :: 3.11
Classifier: Programming Language :: Python :: 3.12
Requires-Dist: aiohttp (>=3.8.0,<4.0.0)
Requires-Dist: protobuf (>=6.31,<7.0)
